{
	"resourceType": "Observation",
	"id": "df5a2807-e0b2-4971-9820-efdbbbfcef7b",
	"meta": {
		"versionId": "1",
		"lastUpdated": "2020-07-21T05:00:12.508+00:00",
		"source": "#IXZkFSi8UrYsA5vD",
		"profile": [
			"http://hl7.org/fhir/us/vrdr/StructureDefinition/VRDR-Decedent-Age"
		]
	},
	"status": "final",
	"code": {
		"coding": [
			{
				"system": "http://loinc.org",
				"code": "30525-0",
				"display": "AGE"
			}
		]
	},
	"subject": {
		"reference": "Patient/51b806c8-566f-463e-8783-9fbf6be8161d"
	},
	"effectiveDateTime": "2020-01-02",
	"valueQuantity": {
		"value": 79,
		"unit": "a"
	}
}