{
  "resourceType" : "Location",
  "id" : "DeathLocationUT-Example1",
  "meta" : {
    "profile" : ["http://hl7.org/fhir/us/vrdr/StructureDefinition/vrdr-death-location"]
  },
  "text" : {
    "status" : "generated",
    "div" : "<div xmlns=\"http://www.w3.org/1999/xhtml\"><p><b>Generated Narrative: Location</b><a name=\"DeathLocationUT-Example1\"> </a></p><div style=\"display: inline-block; background-color: #d9e0e7; padding: 6px; margin: 4px; border: 1px solid #8da1b4; border-radius: 5px; line-height: 60%\"><p style=\"margin-bottom: 0px\">Resource Location &quot;DeathLocationUT-Example1&quot; </p><p style=\"margin-bottom: 0px\">Profile: <a href=\"StructureDefinition-vrdr-death-location.html\">Death Location</a></p></div><p><b>name</b>: Salt Lake Regional Medical Cen</p><p><b>description</b>: Facility</p><p><b>type</b>: Death Location <span style=\"background: LightGoldenRodYellow; margin: 4px; border: 1px solid khaki\"> (<a href=\"CodeSystem-vrdr-location-type-cs.html\">Location Type</a>#death)</span></p><p><b>address</b>: Salt Lake City UT </p></div>"
  },
  "name" : "Salt Lake Regional Medical Cen",
  "description" : "Facility",
  "type" : [{
    "coding" : [{
      "system" : "http://hl7.org/fhir/us/vrdr/CodeSystem/vrdr-location-type-cs",
      "code" : "death"
    }]
  }],
  "address" : {
    "city" : "Salt Lake City",
    "state" : "UT"
  }
}