{
  "resourceType" : "Observation",
  "id" : "MilitaryServiceUT-Example1",
  "meta" : {
    "profile" : ["http://hl7.org/fhir/us/vrdr/StructureDefinition/vrdr-decedent-military-service"]
  },
  "text" : {
    "status" : "generated",
    "div" : "<div xmlns=\"http://www.w3.org/1999/xhtml\"><p><b>Generated Narrative: Observation</b><a name=\"MilitaryServiceUT-Example1\"> </a></p><div style=\"display: inline-block; background-color: #d9e0e7; padding: 6px; margin: 4px; border: 1px solid #8da1b4; border-radius: 5px; line-height: 60%\"><p style=\"margin-bottom: 0px\">Resource Observation &quot;MilitaryServiceUT-Example1&quot; </p><p style=\"margin-bottom: 0px\">Profile: <a href=\"StructureDefinition-vrdr-decedent-military-service.html\">Decedent Military Service</a></p></div><p><b>status</b>: final</p><p><b>code</b>: Military service Narrative <span style=\"background: LightGoldenRodYellow; margin: 4px; border: 1px solid khaki\"> (<a href=\"https://loinc.org/\">LOINC</a>#55280-2)</span></p><p><b>subject</b>: <a href=\"Patient-DecedentUT-Example1.html\">Patient/DecedentUT-Example1</a> &quot; LINEBERRY&quot;</p><p><b>value</b>: No <span style=\"background: LightGoldenRodYellow; margin: 4px; border: 1px solid khaki\"> (<a href=\"http://hl7.org/fhir/R4/v2/0136/index.html\">v2 Y/N Indicator</a>#N)</span></p></div>"
  },
  "status" : "final",
  "code" : {
    "coding" : [{
      "system" : "http://loinc.org",
      "code" : "55280-2"
    }]
  },
  "subject" : {
    "reference" : "Patient/DecedentUT-Example1"
  },
  "valueCodeableConcept" : {
    "coding" : [{
      "system" : "http://terminology.hl7.org/CodeSystem/v2-0136",
      "code" : "N",
      "display" : "No"
    }]
  }
}